slcli/__init__.py
slcli/keyreader.py
slcli/sl_cli.py
slcli/apis/__init__.py
slcli/apis/api.py
slcli/apis/platsuppslag.py
slcli/apis/reseplanerare3_1-journeydetail.py
slcli/apis/reseplanerare3_1-trip.py
slcli/apis/reseplanerare3_1.py
slcli/resources/__init__.py
slcli/resources/locations.xml
slcli/test/__init__.py
slcli/test/test_api.py
slcli/test/test_cli.py
slcli/test/test_keyreader.py
slcli/test/test_wrappers.py
SL_CLI-3.3.dist-info/LICENSE
SL_CLI-3.3.dist-info/METADATA
SL_CLI-3.3.dist-info/WHEEL
SL_CLI-3.3.dist-info/entry_points.txt
SL_CLI-3.3.dist-info/top_level.txt
SL_CLI-3.3.dist-info/RECORD
